feedgenerator/__init__.py
feedgenerator/django/__init__.py
feedgenerator/django/utils/__init__.py
feedgenerator/django/utils/datetime_safe.py
feedgenerator/django/utils/encoding.py
feedgenerator/django/utils/feedgenerator.py
feedgenerator/django/utils/functional.py
feedgenerator/django/utils/six.py
feedgenerator/django/utils/timezone.py
feedgenerator/django/utils/xmlutils.py
feedgenerator-2.1.0.dist-info/LICENSE
feedgenerator-2.1.0.dist-info/METADATA
feedgenerator-2.1.0.dist-info/WHEEL
feedgenerator-2.1.0.dist-info/top_level.txt
feedgenerator-2.1.0.dist-info/RECORD
